proxy_enabled_api/__init__.py
proxy_enabled_api/api.py
proxy_enabled_api/dataclasses.py
proxy_enabled_api/proxies.py
proxy_enabled_api/taxonomies.py
proxy_enabled_api-0.0.3.dist-info/LICENSE
proxy_enabled_api-0.0.3.dist-info/METADATA
proxy_enabled_api-0.0.3.dist-info/WHEEL
proxy_enabled_api-0.0.3.dist-info/top_level.txt
proxy_enabled_api-0.0.3.dist-info/RECORD
