Metadata-Version: 2.1
Name: proxy-enabled-api
Version: 0.0.3
Summary: Asynchronous API (in Python)
Author-email: Jake Ballantyne <jake.david.ballantyne@gmail.com>
Maintainer-email: Jake Ballantyne <jake.david.ballantyne@gmail.com>
Project-URL: Homepage, https://github.com/jbal/proxy-enabled-api
Project-URL: Issues, https://github.com/jbal/proxy-enabled-api/issues
Project-URL: Repository, https://github.com/jbal/proxy-enabled-api
Keywords: API
Classifier: License :: OSI Approved :: MIT License
Classifier: Operating System :: OS Independent
Classifier: Programming Language :: Python :: 3
Classifier: Programming Language :: Python :: 3 :: Only
Classifier: Programming Language :: Python :: 3.10
Classifier: Programming Language :: Python :: 3.11
Classifier: Programming Language :: Python :: 3.12
Requires-Python: >=3.10
License-File: LICENSE
Provides-Extra: dev
Requires-Dist: pre-commit (>=2.20.0) ; extra == 'dev'
Provides-Extra: test
